[
    {"edificio_id":"1", "nivel":"0","tiempo":"0"},
    {"edificio_id":"1", "nivel":"1","tiempo":"10"},
    {"edificio_id":"1", "nivel":"2","tiempo":"30"},
    {"edificio_id":"1", "nivel":"3","tiempo":"90"},
    {"edificio_id":"1", "nivel":"4","tiempo":"250"},
    {"edificio_id":"1", "nivel":"5","tiempo":"600"},
    {"edificio_id":"1", "nivel":"6","tiempo":"1500"},
    {"edificio_id":"1", "nivel":"7","tiempo":"5000"},
    {"edificio_id":"1", "nivel":"8","tiempo":"25000"},
    {"edificio_id":"1", "nivel":"9","tiempo":"100000"},
    {"edificio_id":"1", "nivel":"10","tiempo":"500000"},
    
    {"edificio_id":"2", "nivel":"0","tiempo":"0"},
    {"edificio_id":"2", "nivel":"1","tiempo":"10"},
    {"edificio_id":"2", "nivel":"2","tiempo":"30"},
    {"edificio_id":"2", "nivel":"3","tiempo":"90"},
    {"edificio_id":"2", "nivel":"4","tiempo":"250"},
    {"edificio_id":"2", "nivel":"5","tiempo":"600"},
    {"edificio_id":"2", "nivel":"6","tiempo":"1500"},
    {"edificio_id":"2", "nivel":"7","tiempo":"5000"},
    {"edificio_id":"2", "nivel":"8","tiempo":"25000"},
    {"edificio_id":"2", "nivel":"9","tiempo":"100000"},
    {"edificio_id":"2", "nivel":"10","tiempo":"500000"},
    
    {"edificio_id":"3", "nivel":"0","tiempo":"0"},
    {"edificio_id":"3", "nivel":"1","tiempo":"10"},
    {"edificio_id":"3", "nivel":"2","tiempo":"30"},
    {"edificio_id":"3", "nivel":"3","tiempo":"90"},
    {"edificio_id":"3", "nivel":"4","tiempo":"250"},
    {"edificio_id":"3", "nivel":"5","tiempo":"600"},
    {"edificio_id":"3", "nivel":"6","tiempo":"1500"},
    {"edificio_id":"3", "nivel":"7","tiempo":"5000"},
    {"edificio_id":"3", "nivel":"8","tiempo":"25000"},
    {"edificio_id":"3", "nivel":"9","tiempo":"100000"},
    {"edificio_id":"3", "nivel":"10","tiempo":"500000"},
    
    {"edificio_id":"4", "nivel":"0","tiempo":"0"},
    {"edificio_id":"4", "nivel":"1","tiempo":"10"},
    {"edificio_id":"4", "nivel":"2","tiempo":"30"},
    {"edificio_id":"4", "nivel":"3","tiempo":"90"},
    {"edificio_id":"4", "nivel":"4","tiempo":"250"},
    {"edificio_id":"4", "nivel":"5","tiempo":"600"},
    {"edificio_id":"4", "nivel":"6","tiempo":"1500"},
    {"edificio_id":"4", "nivel":"7","tiempo":"5000"},
    {"edificio_id":"4", "nivel":"8","tiempo":"25000"},
    {"edificio_id":"4", "nivel":"9","tiempo":"100000"},
    {"edificio_id":"4", "nivel":"10","tiempo":"500000"}

]